bardolph/__init__.py
bardolph/controller/__init__.py
bardolph/controller/arg_helper.py
bardolph/controller/code_segment.py
bardolph/controller/color_matrix.py
bardolph/controller/config_values.py
bardolph/controller/get_key.py
bardolph/controller/i_controller.py
bardolph/controller/lifx_lan_api.py
bardolph/controller/lifx_lan_light.py
bardolph/controller/light.py
bardolph/controller/light_exception.py
bardolph/controller/light_module.py
bardolph/controller/light_set.py
bardolph/controller/ls_asm.py
bardolph/controller/ls_module.py
bardolph/controller/lsc.py
bardolph/controller/lsc_template.py
bardolph/controller/routine.py
bardolph/controller/run.py
bardolph/controller/script_job.py
bardolph/controller/snapshot.py
bardolph/controller/units.py
bardolph/controller/virtual_light.py
bardolph/fakes/__init__.py
bardolph/fakes/activity_monitor.py
bardolph/fakes/fake_clock.py
bardolph/fakes/fake_light.py
bardolph/fakes/fake_light_api.py
bardolph/lib/__init__.py
bardolph/lib/cache.py
bardolph/lib/clock.py
bardolph/lib/color.py
bardolph/lib/i_lib.py
bardolph/lib/injection.py
bardolph/lib/job_control.py
bardolph/lib/log_config.py
bardolph/lib/noneable.py
bardolph/lib/object_list_output.py
bardolph/lib/param_helper.py
bardolph/lib/retry.py
bardolph/lib/settings.py
bardolph/lib/sorted_list.py
bardolph/lib/std_out_output.py
bardolph/lib/symbol.py
bardolph/lib/symbol_table.py
bardolph/lib/time_pattern.py
bardolph/lib/trace.py
bardolph/parser/__init__.py
bardolph/parser/code_gen.py
bardolph/parser/context.py
bardolph/parser/expr_parser.py
bardolph/parser/io_parser.py
bardolph/parser/lex.py
bardolph/parser/light_list_parser.py
bardolph/parser/loop_parser.py
bardolph/parser/matrix_parser.py
bardolph/parser/optimizer.py
bardolph/parser/parse.py
bardolph/parser/sub_parser.py
bardolph/parser/token.py
bardolph/runtime/__init__.py
bardolph/runtime/bardolph_fn.py
bardolph/runtime/bardolph_math.py
bardolph/runtime/i_runtime.py
bardolph/runtime/query.py
bardolph/runtime/runtime_module.py
bardolph-0.3.0.dist-info/METADATA
bardolph-0.3.0.dist-info/WHEEL
bardolph-0.3.0.dist-info/entry_points.txt
bardolph-0.3.0.dist-info/top_level.txt
bardolph-0.3.0.dist-info/RECORD
