Metadata-Version: 2.4
Name: bardolph
Version: 0.3.0
Summary: Simple scripting language for LIFX lights
Author-email: Bardolph Automation <info@bardolphauto.com>
License-Expression: Apache-2.0
Project-URL: Homepage, https://www.bardolph.org
Project-URL: Repository, https://github.com/Bardolph-Automation-Inc/bardolph
Classifier: Programming Language :: Python :: 3.10
Classifier: Programming Language :: Python :: 3.11
Classifier: Programming Language :: Python :: 3.12
Classifier: Programming Language :: Python :: 3.13
Classifier: Programming Language :: Python :: 3.14
Classifier: Operating System :: OS Independent
Classifier: Development Status :: 4 - Beta
Requires-Python: >=3.10
Requires-Dist: lifxlan>=1.2.9
Provides-Extra: web
Requires-Dist: Flask; extra == "web"
Requires-Dist: waitress; extra == "web"
